{
  "metadata": {
    "generated_date": "2024-12-30T19:16:00",
    "total_messages": 287,
    "timezone": "America/Los_Angeles",
    "participants": {
      "parents": [
        "Robert Moyer",
        "Christine Moyer"
      ],
      "children": [
        "Adrian Moyer",
        "Max Moyer"
      ],
      "third_party": [
        "Message 1 of 287"
      ]
    }
  },
  "threads": {
    "Re: Condo Sale\nOn 11/30/2024 at 03:09 PM, Christine Moyer wrote:": [
      "msg_0001"
    ],
    "Re: Expenses prior to Oct 31\nOn 11/30/2024 at 07:49 PM, Robert Moyer wrote:": [
      "msg_0002"
    ],
    "Re: Expenses prior to Oct 31\nOn 12/01/2024 at 07:30 AM, Christine Moyer wrote:": [
      "msg_0004"
    ],
    "Re: Sunday Dec 8\nOn 12/01/2024 at 10:47 AM, Christine Moyer wrote:": [
      "msg_0005"
    ],
    "Re: Expenses prior to Oct 31\nOn 12/01/2024 at 11:04 AM, Robert Moyer wrote:": [
      "msg_0006"
    ],
    "Re: Expenses prior to Oct 31\nOn 12/01/2024 at 03:03 PM, Christine Moyer wrote:": [
      "msg_0008"
    ],
    "Re: Sunday Dec 8\nOn 12/01/2024 at 03:04 PM, Christine Moyer wrote:": [
      "msg_0009",
      "msg_0032"
    ],
    "Re: Monthly transfer\nOn 12/02/2024 at 08:19 AM, Christine Moyer wrote:": [
      "msg_0011"
    ],
    "Re: Monthly transfer": [
      "msg_0012"
    ],
    "Re: Monthly transfer\nOn 12/02/2024 at 09:41 AM, Robert Moyer wrote:": [
      "msg_0013"
    ],
    "Re: SafeCo Car Insurance/Split\nOn 11/29/2024 at 12:19 PM, Christine Moyer wrote:": [
      "msg_0014"
    ],
    "Re: SafeCo Car Insurance/Split\nOn 12/02/2024 at 01:11 PM, Christine Moyer wrote:": [
      "msg_0015"
    ],
    "Re: Hole in wall\nOn 12/02/2024 at 03:06 PM, Christine Moyer wrote:": [
      "msg_0020"
    ],
    "Re: SAAS Tuition December\nOn 12/02/2024 at 03:15 PM, Christine Moyer wrote:": [
      "msg_0021"
    ],
    "Re: SAAS Tuition December": [
      "msg_0022"
    ],
    "Re: SAAS Tuition December\nOn 12/02/2024 at 04:05 PM, Robert Moyer wrote:": [
      "msg_0023"
    ],
    "Re: Expenses prior to Oct 31": [
      "msg_0024"
    ],
    "Re: Max passport / fees\nOn 12/03/2024 at 03:39 PM, Christine Moyer wrote:": [
      "msg_0028"
    ],
    "Re: Max passport / fees\nOn 12/03/2024 at 04:54 PM, Christine Moyer wrote:": [
      "msg_0029"
    ],
    "Re: Max passport / fees\nOn 12/03/2024 at 04:55 PM, Robert Moyer wrote:": [
      "msg_0030"
    ],
    "Re: Max passport / fees\nOn 12/03/2024 at 04:59 PM, Christine Moyer wrote:": [
      "msg_0031"
    ],
    "Re: Sunday Dec 8\nOn 12/06/2024 at 06:31 PM, Robert Moyer wrote:": [
      "msg_0038",
      "msg_0083"
    ],
    "Re: Sunday Dec 8\nOn 12/07/2024 at 11:05 AM, Robert Moyer wrote:": [
      "msg_0039"
    ],
    "Re: What Happened Today\nOn 12/07/2024 at 12:51 PM, Christine Moyer wrote:": [
      "msg_0041"
    ],
    "Re: What Happened Today\nOn 12/07/2024 at 12:59 PM, Robert Moyer wrote:": [
      "msg_0042"
    ],
    "Re: What Happened Today\nOn 12/08/2024 at 09:53 AM, Robert Moyer wrote:": [
      "msg_0044"
    ],
    "Re: What Happened Today\nOn 12/08/2024 at 03:46 PM, Christine Moyer wrote:": [
      "msg_0046"
    ],
    "Re: What Happened Today\nOn 12/08/2024 at 04:33 PM, Robert Moyer wrote:": [
      "msg_0049"
    ],
    "Re: What Happened Today\nOn 12/08/2024 at 04:54 PM, Christine Moyer wrote:": [
      "msg_0050"
    ],
    "Re: What Happened Today\nOn 12/08/2024 at 05:00 PM, Robert Moyer wrote:": [
      "msg_0051"
    ],
    "Re: What Happened Today\nOn 12/08/2024 at 05:48 PM, Robert Moyer wrote:": [
      "msg_0056"
    ],
    "Re: It has not been entered into court\nOn 12/09/2024 at 11:13 AM, Robert Moyer wrote:": [
      "msg_0057"
    ],
    "Re: What Happened Today\nOn 12/09/2024 at 12:28 PM, Christine Moyer wrote:": [
      "msg_0058"
    ],
    "Re: It has not been entered into court\nOn 12/09/2024 at 12:29 PM, Christine Moyer wrote:": [
      "msg_0059"
    ],
    "Re: SAAS backcountry\nOn 12/10/2024 at 07:02 AM, Christine Moyer wrote:": [
      "msg_0061"
    ],
    "Re: SAAS backcountry\nOn 12/10/2024 at 07:24 AM, Christine Moyer wrote:": [
      "msg_0063"
    ],
    "Re: SAAS backcountry\nOn 12/10/2024 at 07:26 AM, Robert Moyer wrote:": [
      "msg_0065"
    ],
    "Re: Happy Anniversary\nOn 12/10/2024 at 07:28 AM, Robert Moyer wrote:": [
      "msg_0066"
    ],
    "Re: SAAS backcountry\nOn 12/10/2024 at 09:47 AM, Christine Moyer wrote:": [
      "msg_0067"
    ],
    "Re: SAAS backcountry\nOn 12/10/2024 at 09:48 AM, Robert Moyer wrote:": [
      "msg_0069"
    ],
    "Re: SAAS backcountry": [
      "msg_0070"
    ],
    "Re: Safeco/Fidelity": [
      "msg_0071"
    ],
    "Re: SAAS backcountry\nOn 12/10/2024 at 10:08 AM, Robert Moyer wrote:": [
      "msg_0072"
    ],
    "Re: Safeco/Fidelity\nOn 12/10/2024 at 10:21 AM, Robert Moyer wrote:": [
      "msg_0073"
    ],
    "Re: SAAS backcountry\nOn 12/10/2024 at 10:43 AM, Christine Moyer wrote:": [
      "msg_0074"
    ],
    "Re: SAAS backcountry\nOn 12/10/2024 at 10:51 AM, Robert Moyer wrote:": [
      "msg_0075"
    ],
    "Re: SAAS backcountry\nOn 12/10/2024 at 11:04 AM, Christine Moyer wrote:": [
      "msg_0076"
    ],
    "Re: SAAS backcountry\nOn 12/10/2024 at 11:23 AM, Robert Moyer wrote:": [
      "msg_0078"
    ],
    "Re: Drop Off\nOn 12/10/2024 at 12:16 PM, Robert Moyer wrote:": [
      "msg_0080"
    ],
    "Re: Expenses prior to Oct 31\nOn 12/03/2024 at 10:55 AM, Christine Moyer wrote:": [
      "msg_0081"
    ],
    "Re: House repairs/ tree/yard\nOn 12/02/2024 at 02:59 PM, Christine Moyer wrote:": [
      "msg_0082"
    ],
    "Re: House repairs/ tree/yard\nOn 12/10/2024 at 05:55 PM, Christine Moyer wrote:": [
      "msg_0084"
    ],
    "Re: Sunday Dec 8\nOn 12/10/2024 at 07:54 PM, Christine Moyer wrote:": [
      "msg_0085"
    ],
    "Re: Drop Off\nOn 12/10/2024 at 05:49 PM, Christine Moyer wrote:": [
      "msg_0086"
    ],
    "Re: Sunday Dec 8\nOn 12/10/2024 at 07:58 PM, Robert Moyer wrote:": [
      "msg_0088"
    ],
    "Re: Trip authorization\nOn 12/11/2024 at 05:35 PM, Christine Moyer wrote:": [
      "msg_0091"
    ],
    "Re: House repairs/ tree/yard": [
      "msg_0092"
    ],
    "Re: Safeco/Fidelity\nOn 12/10/2024 at 10:47 AM, Christine Moyer wrote:": [
      "msg_0094"
    ],
    "Re: Developer Weeks\nOn 12/11/2024 at 10:17 PM, Robert Moyer wrote:": [
      "msg_0097"
    ],
    "Re: Safeco/Fidelity\nOn 12/11/2024 at 10:06 PM, Robert Moyer wrote:": [
      "msg_0098"
    ],
    "Re: Expenses prior to Oct 31\nOn 12/11/2024 at 09:29 PM, Robert Moyer wrote:": [
      "msg_0099"
    ],
    "Re: Developer Weeks\nOn 12/12/2024 at 06:28 AM, Christine Moyer wrote:": [
      "msg_0101"
    ],
    "Re: Safeco/Fidelity\nOn 12/12/2024 at 06:29 AM, Christine Moyer wrote:": [
      "msg_0102"
    ],
    "Re: Safeco/Fidelity\nOn 12/12/2024 at 06:31 AM, Christine Moyer wrote:": [
      "msg_0103"
    ],
    "Re: Safeco/Fidelity\nOn 12/12/2024 at 06:38 AM, Robert Moyer wrote:": [
      "msg_0104"
    ],
    "Re: Adrian today\nOn 12/12/2024 at 06:59 AM, Christine Moyer wrote:": [
      "msg_0106"
    ],
    "Re: Adrian today\nOn 12/12/2024 at 07:23 AM, Christine Moyer wrote:": [
      "msg_0107"
    ],
    "Re: Adrian today\nOn 12/12/2024 at 07:25 AM, Robert Moyer wrote:": [
      "msg_0108"
    ],
    "Re: Safeco/Fidelity\nOn 12/12/2024 at 06:58 AM, Christine Moyer wrote:": [
      "msg_0110"
    ],
    "Re: Connor\nOn 12/12/2024 at 08:34 AM, Robert Moyer wrote:": [
      "msg_0111"
    ],
    "Re: Safeco/Fidelity\nOn 12/12/2024 at 08:40 AM, Christine Moyer wrote:": [
      "msg_0112"
    ],
    "Re: Safeco/Fidelity\nOn 12/12/2024 at 08:44 AM, Robert Moyer wrote:": [
      "msg_0113"
    ],
    "Re: Adrian\nOn 12/12/2024 at 11:11 AM, Robert Moyer wrote:": [
      "msg_0115"
    ],
    "Re: Health Insurance\nOn 12/12/2024 at 02:02 PM, Robert Moyer wrote:": [
      "msg_0117"
    ],
    "Re: Safeco/Fidelity\nOn 12/12/2024 at 09:32 AM, Robert Moyer wrote:": [
      "msg_0118"
    ],
    "Re: Safeco/Fidelity\nOn 12/12/2024 at 03:51 PM, Christine Moyer wrote:": [
      "msg_0120"
    ],
    "Re: Safeco/Fidelity\nOn 12/12/2024 at 03:57 PM, Robert Moyer wrote:": [
      "msg_0121"
    ],
    "Re: Fidelity\nOn 12/13/2024 at 09:34 AM, Robert Moyer wrote:": [
      "msg_0127"
    ],
    "Re: Adrian\nOn 12/13/2024 at 07:37 AM, Christine Moyer wrote:": [
      "msg_0129"
    ],
    "Re: Adrian\nOn 12/13/2024 at 02:59 PM, Robert Moyer wrote:": [
      "msg_0132"
    ],
    "Re: Adrian\nOn 12/13/2024 at 03:06 PM, Christine Moyer wrote:": [
      "msg_0133"
    ],
    "Breakfast": [
      "msg_0134"
    ],
    "Re: Adrian\nOn 12/13/2024 at 03:11 PM, Robert Moyer wrote:": [
      "msg_0135"
    ],
    "Re: Adrian\nOn 12/13/2024 at 05:52 PM, Robert Moyer wrote:": [
      "msg_0136"
    ],
    "Re: Adrian\nOn 12/13/2024 at 07:39 PM, Christine Moyer wrote:": [
      "msg_0137"
    ],
    "Re: Adrian\nOn 12/13/2024 at 07:49 PM, Robert Moyer wrote:": [
      "msg_0138"
    ],
    "Re: Adrian\nOn 12/13/2024 at 08:19 PM, Robert Moyer wrote:": [
      "msg_0139"
    ],
    "Re: Adrian\nOn 12/14/2024 at 01:59 AM, Robert Moyer wrote:": [
      "msg_0140"
    ],
    "Re: Adrian\nOn 12/14/2024 at 06:57 AM, Christine Moyer wrote:": [
      "msg_0141"
    ],
    "Re: Adrian\nOn 12/14/2024 at 07:58 AM, Robert Moyer wrote:": [
      "msg_0142"
    ],
    "Re: Adrian": [
      "msg_0144"
    ],
    "Re: Adrian\nOn 12/14/2024 at 01:18 PM, Robert Moyer wrote:": [
      "msg_0145"
    ],
    "Re: Adrian\nOn 12/14/2024 at 02:46 PM, Robert Moyer wrote:": [
      "msg_0147"
    ],
    "Re: Adrian\nOn 12/14/2024 at 02:56 PM, Robert Moyer wrote:": [
      "msg_0148"
    ],
    "Re: Adrian\nOn 12/14/2024 at 03:01 PM, Christine Moyer wrote:": [
      "msg_0149"
    ],
    "Re: Adrian\nOn 12/14/2024 at 03:12 PM, Christine Moyer wrote:": [
      "msg_0151"
    ],
    "Re: Adrian\nOn 12/14/2024 at 03:28 PM, Robert Moyer wrote:": [
      "msg_0152"
    ],
    "Re: Health Insurance\nOn 12/13/2024 at 07:25 AM, Christine Moyer wrote:": [
      "msg_0155"
    ],
    "Re: Seahawks Tickets - Dec 22\nOn 12/15/2024 at 05:46 PM, Christine Moyer wrote:": [
      "msg_0156"
    ],
    "Re: Basketball\nOn 12/15/2024 at 05:52 PM, Robert Moyer wrote:": [
      "msg_0158"
    ],
    "Re: Basketball\nOn 12/15/2024 at 05:53 PM, Christine Moyer wrote:": [
      "msg_0159"
    ],
    "Re: Basketball\nOn 12/15/2024 at 05:56 PM, Robert Moyer wrote:": [
      "msg_0161"
    ],
    "Re: Seahawks Tickets - Dec 22\nOn 12/15/2024 at 05:58 PM, Christine Moyer wrote:": [
      "msg_0162"
    ],
    "Re: Basketball\nOn 12/15/2024 at 05:59 PM, Christine Moyer wrote:": [
      "msg_0163"
    ],
    "Re: Breakthrough Moment\nOn 12/15/2024 at 08:22 PM, Robert Moyer wrote:": [
      "msg_0166"
    ],
    "Re: Seahawks Tickets - Dec 22\nOn 12/15/2024 at 11:50 PM, Christine Moyer wrote:": [
      "msg_0167"
    ],
    "Re: Breakthrough Moment\nOn 12/16/2024 at 10:18 AM, Christine Moyer wrote:": [
      "msg_0170"
    ],
    "Re: Breakthrough Moment\nOn 12/16/2024 at 10:20 AM, Robert Moyer wrote:": [
      "msg_0171"
    ],
    "Re: Breakthrough Moment\nOn 12/16/2024 at 10:21 AM, Christine Moyer wrote:": [
      "msg_0172"
    ],
    "Re: Breakthrough Moment\nOn 12/16/2024 at 10:33 AM, Christine Moyer wrote:": [
      "msg_0174"
    ],
    "Re: Parent Coordinator\nOn 12/16/2024 at 03:30 PM, Robert Moyer wrote:": [
      "msg_0176"
    ],
    "Extra Mortgage Payment\nOn 12/16/2024 at 10:20 AM, Christine Moyer wrote:": [
      "msg_0178"
    ],
    "Re: Fidelity acct - msft dividends and share deposit\nOn 12/17/2024 at 08:57 AM, Christine Moyer wrote:": [
      "msg_0180"
    ],
    "Re: Fidelity acct - msft dividends and share deposit\nOn 12/17/2024 at 08:59 AM, Robert Moyer wrote:": [
      "msg_0182"
    ],
    "Re: Extra Mortgage Payment\nOn 12/17/2024 at 09:00 AM, Robert Moyer wrote:": [
      "msg_0183"
    ],
    "Re: Fidelity acct - msft dividends and share deposit\nOn 12/17/2024 at 10:28 AM, Christine Moyer wrote:": [
      "msg_0184"
    ],
    "Re: Extra Mortgage Payment\nOn 12/17/2024 at 10:29 AM, Christine Moyer wrote:": [
      "msg_0185"
    ],
    "Re: Fidelity acct - msft dividends and share deposit\nOn 12/17/2024 at 10:30 AM, Robert Moyer wrote:": [
      "msg_0186"
    ],
    "Re: Extra Mortgage Payment\nOn 12/17/2024 at 10:32 AM, Robert Moyer wrote:": [
      "msg_0187"
    ],
    "Re: Extra Mortgage Payment\nOn 12/17/2024 at 10:34 AM, Christine Moyer wrote:": [
      "msg_0188"
    ],
    "Re: Fidelity acct - msft dividends and share deposit\nOn 12/17/2024 at 10:33 AM, Christine Moyer wrote:": [
      "msg_0189"
    ],
    "Re: Running List\nOn 12/17/2024 at 12:55 PM, Robert Moyer wrote:": [
      "msg_0191"
    ],
    "Re: Running List\nOn 12/17/2024 at 02:56 PM, Christine Moyer wrote:": [
      "msg_0193"
    ],
    "Re: Running List\nOn 12/17/2024 at 03:09 PM, Robert Moyer wrote:": [
      "msg_0194"
    ],
    "Re: Running List\nOn 12/17/2024 at 03:41 PM, Robert Moyer wrote:": [
      "msg_0195"
    ],
    "Re: Running List\nOn 12/17/2024 at 06:06 PM, Christine Moyer wrote:": [
      "msg_0196"
    ],
    "Re: Running List\nOn 12/17/2024 at 06:16 PM, Robert Moyer wrote:": [
      "msg_0197"
    ],
    "Email will erectile dysfunction listings": [
      "msg_0198"
    ],
    "Re: Email will erectile dysfunction listings\nOn 12/18/2024 at 07:06 AM, Christine Moyer wrote:": [
      "msg_0200"
    ],
    "Re: Adrian\u2019s Marh\nOn 12/18/2024 at 10:49 AM, Robert Moyer wrote:": [
      "msg_0201"
    ],
    "Re: Email will erectile dysfunction listings\nOn 12/18/2024 at 11:16 AM, Robert Moyer wrote:": [
      "msg_0202"
    ],
    "Re: Adrian\u2019s Marh\nOn 12/18/2024 at 11:32 AM, Christine Moyer wrote:": [
      "msg_0203"
    ],
    "Re: Email will erectile dysfunction listings\nOn 12/18/2024 at 11:38 AM, Christine Moyer wrote:": [
      "msg_0204"
    ],
    "Re: Adrian\u2019s Math\nOn 12/18/2024 at 12:19 PM, Robert Moyer wrote:": [
      "msg_0206"
    ],
    "Re: Adrian\u2019s Math": [
      "msg_0207"
    ],
    "Re: Adrian\u2019s Math\nOn 12/19/2024 at 01:07 PM, Christine Moyer wrote:": [
      "msg_0208"
    ],
    "Re: Adrian\u2019s Math\nOn 12/19/2024 at 01:18 PM, Christine Moyer wrote:": [
      "msg_0210"
    ],
    "Re: Adrian\u2019s Math\nOn 12/19/2024 at 01:42 PM, Robert Moyer wrote:": [
      "msg_0211"
    ],
    "Re: Adrian\u2019s Math\nOn 12/19/2024 at 03:25 PM, Christine Moyer wrote:": [
      "msg_0213"
    ],
    "Re: Email will erectile dysfunction listings\nOn 12/18/2024 at 11:39 AM, Robert Moyer wrote:": [
      "msg_0214"
    ],
    "Re: Adrian\u2019s Math\nOn 12/19/2024 at 03:37 PM, Robert Moyer wrote:": [
      "msg_0215"
    ],
    "Re: Signal?\nOn 12/20/2024 at 02:07 PM, Robert Moyer wrote:": [
      "msg_0218"
    ],
    "Re: Signal?\nOn 12/20/2024 at 07:08 PM, Christine Moyer wrote:": [
      "msg_0219"
    ],
    "Re: Alan\nOn 12/21/2024 at 02:36 PM, Christine Moyer wrote:": [
      "msg_0221"
    ],
    "Re: Alan\nOn 12/21/2024 at 02:37 PM, Robert Moyer wrote:": [
      "msg_0222"
    ],
    "Re: Alan\nOn 12/22/2024 at 12:23 PM, Robert Moyer wrote:": [
      "msg_0223"
    ],
    "Re: Alan\nOn 12/22/2024 at 01:20 PM, Christine Moyer wrote:": [
      "msg_0224"
    ],
    "Re: Fidelity - MSFT Dividend transfer\nOn 12/22/2024 at 02:51 PM, Christine Moyer wrote:": [
      "msg_0226"
    ],
    "Re: No Response Requested\nOn 12/24/2023 at 08:13 PM, Robert Moyer wrote:": [
      "msg_0227"
    ],
    "Re: No Response Requested\nOn 12/24/2024 at 12:05 PM, Christine Moyer wrote:": [
      "msg_0229"
    ],
    "Re: No Response Requested\nOn 12/24/2024 at 12:07 PM, Robert Moyer wrote:": [
      "msg_0230"
    ],
    "Re: No Response Requested\nOn 12/24/2024 at 12:31 PM, Robert Moyer wrote:": [
      "msg_0232"
    ],
    "Re: No Response Requested\nOn 12/24/2024 at 12:44 PM, Robert Moyer wrote:": [
      "msg_0233"
    ],
    "Re: No Response Requested\nOn 12/24/2024 at 01:21 PM, Christine Moyer wrote:": [
      "msg_0234",
      "msg_0242"
    ],
    "Re: Fidelity - MSFT Dividend transfer\nOn 12/23/2024 at 08:23 AM, Robert Moyer wrote:": [
      "msg_0235"
    ],
    "Re: Fidelity - MSFT Dividend transfer\nOn 12/24/2024 at 02:39 PM, Christine Moyer wrote:": [
      "msg_0236"
    ],
    "Re: Fidelity - MSFT Dividend transfer\nOn 12/24/2024 at 02:42 PM, Robert Moyer wrote:": [
      "msg_0237"
    ],
    "Re: Fidelity - MSFT Dividend transfer\nOn 12/25/2024 at 02:18 PM, Christine Moyer wrote:": [
      "msg_0241"
    ],
    "Re: No Response Requested\nOn 12/25/2024 at 04:22 PM, Robert Moyer wrote:": [
      "msg_0243"
    ],
    "Re: Fidelity - MSFT Dividend transfer\nOn 12/25/2024 at 04:35 PM, Christine Moyer wrote:": [
      "msg_0245"
    ],
    "Re: No Response Requested\nOn 12/25/2024 at 04:37 PM, Robert Moyer wrote:": [
      "msg_0248"
    ],
    "Re: Fidelity - MSFT Dividend transfer\nOn 12/25/2024 at 02:19 PM, Robert Moyer wrote:": [
      "msg_0250"
    ],
    "Re: No Response Requested\nOn 12/25/2024 at 04:41 PM, Robert Moyer wrote:": [
      "msg_0251"
    ],
    "Re: No Response Requested\nOn 12/26/2024 at 01:29 PM, Christine Moyer wrote:": [
      "msg_0253"
    ],
    "Re: No Response Requested\nOn 12/26/2024 at 01:33 PM, Robert Moyer wrote:": [
      "msg_0254"
    ],
    "Re: Fidelity - MSFT Dividend transfer\nOn 12/26/2024 at 01:52 PM, Christine Moyer wrote:": [
      "msg_0256"
    ],
    "Re: Fidelity - MSFT Dividend transfer\nOn 12/26/2024 at 02:09 PM, Robert Moyer wrote:": [
      "msg_0257"
    ],
    "Re: No Response Requested\nOn 12/26/2024 at 01:49 PM, Christine Moyer wrote:": [
      "msg_0258"
    ],
    "Re: Fidelity - MSFT Dividend transfer\nOn 12/28/2024 at 08:46 AM, Christine Moyer wrote:": [
      "msg_0261"
    ],
    "Re: Fidelity - MSFT Dividend transfer\nOn 12/28/2024 at 09:01 AM, Christine Moyer wrote:": [
      "msg_0264"
    ],
    "Re: AD is asleep\nOn 12/28/2024 at 09:01 AM, Robert Moyer wrote:": [
      "msg_0265"
    ],
    "Re: AD is asleep\nOn 12/28/2024 at 09:39 AM, Robert Moyer wrote:": [
      "msg_0266"
    ],
    "Re: Fidelity - MSFT Dividend transfer\nOn 12/28/2024 at 09:01 AM, Robert Moyer wrote:": [
      "msg_0267"
    ],
    "Seahawks ticket sale": [
      "msg_0269"
    ],
    "Re: AD is asleep": [
      "msg_0272"
    ],
    "Re: AD is asleep\nOn 12/28/2024 at 11:05 AM, Robert Moyer wrote:": [
      "msg_0274"
    ],
    "Re: Seahawks ticket sale\nOn 12/28/2024 at 03:50 PM, Christine Moyer wrote:": [
      "msg_0277"
    ],
    "Re: AD is asleep\nOn 12/28/2024 at 03:50 PM, Robert Moyer wrote:": [
      "msg_0278"
    ],
    "Re: AD is asleep\nOn 12/28/2024 at 04:06 PM, Christine Moyer wrote:": [
      "msg_0279"
    ],
    "Re: Thursday\nOn 12/28/2024 at 08:00 PM, Christine Moyer wrote:": [
      "msg_0282"
    ],
    "Re: Drop Off\nOn 12/10/2024 at 07:59 PM, Robert Moyer wrote:": [
      "msg_0287"
    ]
  }
}